slurmit/__about__.py
slurmit/__init__.py
slurmit/core.py
slurmit-0.0.3.dist-info/METADATA
slurmit-0.0.3.dist-info/WHEEL
slurmit-0.0.3.dist-info/licenses/LICENSE
slurmit-0.0.3.dist-info/RECORD
