Metadata-Version: 2.4
Name: slurmit
Version: 0.0.3
Project-URL: Documentation, https://moskomule.github.io/slurmit
Project-URL: Issues, https://github.com/moskomule/slurmit/issues
Project-URL: Source, https://github.com/moskomule/slurmit
Author-email: Ryuichiro Hataya <moskomule@users.noreply.github.com>
License-Expression: MIT
License-File: LICENSE
Classifier: Development Status :: 4 - Beta
Classifier: Programming Language :: Python
Classifier: Programming Language :: Python :: 3.11
Classifier: Programming Language :: Python :: 3.12
Classifier: Programming Language :: Python :: 3.13
Classifier: Programming Language :: Python :: Implementation :: CPython
Requires-Python: >=3.11
Requires-Dist: cloudpickle
